{
  "updated_at": "2026-07-02T19:02:52+09:00",
  "sectors": [
    {
      "sector_code": "G10",
      "sector_name": "에너지",
      "etfs": [
        {
          "ticker": "117460",
          "name": "KODEX 에너지화학",
          "provider": "삼성자산운용",
          "nav": 13129.0,
          "return_1m": null,
          "return_3m": -10.1854
        },
        {
          "ticker": "139250",
          "name": "TIGER 200 에너지화학",
          "provider": "미래에셋자산운용",
          "nav": 17588.0,
          "return_1m": null,
          "return_3m": 12.5812
        }
      ]
    },
    {
      "sector_code": "G15",
      "sector_name": "소재",
      "etfs": [
        {
          "ticker": "117680",
          "name": "KODEX 철강",
          "provider": "삼성자산운용",
          "nav": 11295.0,
          "return_1m": null,
          "return_3m": -21.4692
        },
        {
          "ticker": "139240",
          "name": "TIGER 200 철강소재",
          "provider": "미래에셋자산운용",
          "nav": 9920.0,
          "return_1m": null,
          "return_3m": -26.6804
        }
      ]
    },
    {
      "sector_code": "G20",
      "sector_name": "산업재",
      "etfs": [
        {
          "ticker": "117700",
          "name": "KODEX 건설",
          "provider": "삼성자산운용",
          "nav": 6625.0,
          "return_1m": null,
          "return_3m": -7.1669
        },
        {
          "ticker": "102960",
          "name": "KODEX 기계장비",
          "provider": "삼성자산운용",
          "nav": 15325.0,
          "return_1m": null,
          "return_3m": -0.2572
        }
      ]
    },
    {
      "sector_code": "G25",
      "sector_name": "경기소비재",
      "etfs": [
        {
          "ticker": "091180",
          "name": "KODEX 자동차",
          "provider": "삼성자산운용",
          "nav": 30596.0,
          "return_1m": null,
          "return_3m": 0.3061
        },
        {
          "ticker": "139290",
          "name": "TIGER 200 경기소비재",
          "provider": "미래에셋자산운용",
          "nav": 28672.0,
          "return_1m": null,
          "return_3m": 8.5538
        }
      ]
    },
    {
      "sector_code": "G30",
      "sector_name": "필수소비재",
      "etfs": [
        {
          "ticker": "266410",
          "name": "KODEX 필수소비재",
          "provider": "삼성자산운용",
          "nav": 9268.0,
          "return_1m": null,
          "return_3m": -4.912
        },
        {
          "ticker": "227560",
          "name": "TIGER 200 생활소비재",
          "provider": "미래에셋자산운용",
          "nav": 12783.0,
          "return_1m": null,
          "return_3m": -4.0632
        }
      ]
    },
    {
      "sector_code": "G35",
      "sector_name": "건강관리",
      "etfs": [
        {
          "ticker": "143860",
          "name": "TIGER 헬스케어",
          "provider": "미래에셋자산운용",
          "nav": 39211.0,
          "return_1m": null,
          "return_3m": -19.8282
        },
        {
          "ticker": "244580",
          "name": "KODEX 바이오",
          "provider": "삼성자산운용",
          "nav": 9132.0,
          "return_1m": null,
          "return_3m": -25.9013
        }
      ]
    },
    {
      "sector_code": "G40",
      "sector_name": "금융",
      "etfs": [
        {
          "ticker": "091170",
          "name": "KODEX 은행",
          "provider": "삼성자산운용",
          "nav": 15346.0,
          "return_1m": null,
          "return_3m": -1.0732
        },
        {
          "ticker": "102970",
          "name": "KODEX 증권",
          "provider": "삼성자산운용",
          "nav": 21233.0,
          "return_1m": null,
          "return_3m": -15.7599
        },
        {
          "ticker": "139270",
          "name": "TIGER 200 금융",
          "provider": "미래에셋자산운용",
          "nav": 16743.0,
          "return_1m": null,
          "return_3m": 3.6538
        }
      ]
    },
    {
      "sector_code": "G45",
      "sector_name": "IT",
      "etfs": [
        {
          "ticker": "396500",
          "name": "TIGER 반도체TOP10",
          "provider": "미래에셋자산운용",
          "nav": 43228.0,
          "return_1m": null,
          "return_3m": 54.9719
        },
        {
          "ticker": "091160",
          "name": "KODEX 반도체",
          "provider": "삼성자산운용",
          "nav": 147592.0,
          "return_1m": null,
          "return_3m": 76.9093
        },
        {
          "ticker": "139260",
          "name": "TIGER 200 IT",
          "provider": "미래에셋자산운용",
          "nav": 168686.0,
          "return_1m": null,
          "return_3m": 138.8012
        }
      ]
    },
    {
      "sector_code": "G50",
      "sector_name": "통신서비스",
      "etfs": [
        {
          "ticker": "315270",
          "name": "TIGER 200커뮤니케이션서비스",
          "provider": "미래에셋자산운용",
          "nav": 19976.0,
          "return_1m": null,
          "return_3m": -9.6649
        }
      ]
    },
    {
      "sector_code": "G55",
      "sector_name": "유틸리티",
      "etfs": []
    }
  ]
}