{"ticker":"009420","history":[{"date":"2026-03-27","close":63300,"per":106.0,"pbr":19.88,"eps":null,"bps":3184,"roe":-3.37,"debt_ratio":39.3,"market_cap":3306800000000,"dividend_yield":null},{"date":"2026-03-30","close":58300,"per":106.0,"pbr":18.31,"eps":null,"bps":3184,"roe":-3.37,"debt_ratio":39.3,"market_cap":3045600000000,"dividend_yield":null},{"date":"2026-03-31","close":55300,"per":106.0,"pbr":17.37,"eps":null,"bps":3184,"roe":-3.37,"debt_ratio":39.3,"market_cap":2888900000000,"dividend_yield":null}]}