{"ticker":"103140","history":[{"date":"2026-03-27","close":91700,"per":17.46,"pbr":1.09,"eps":5251,"bps":84137,"roe":6.54,"debt_ratio":88.38,"market_cap":2569800000000,"dividend_yield":1.85},{"date":"2026-03-30","close":89700,"per":17.08,"pbr":1.07,"eps":5251,"bps":84137,"roe":6.54,"debt_ratio":88.38,"market_cap":2513700000000,"dividend_yield":1.89},{"date":"2026-03-31","close":86700,"per":16.51,"pbr":1.03,"eps":5251,"bps":84137,"roe":6.54,"debt_ratio":88.38,"market_cap":2429700000000,"dividend_yield":1.96},{"date":"2026-04-01","close":93500,"per":17.81,"pbr":1.11,"eps":5251,"bps":84137,"roe":6.54,"debt_ratio":88.38,"market_cap":2620200000000,"dividend_yield":1.82},{"date":"2026-04-02","close":92700,"per":17.65,"pbr":1.1,"eps":5251,"bps":84137,"roe":6.54,"debt_ratio":88.38,"market_cap":2597800000000,"dividend_yield":1.83},{"date":"2026-04-03","close":96800,"per":18.43,"pbr":1.15,"eps":5251,"bps":84137,"roe":6.54,"debt_ratio":88.38,"market_cap":2712700000000,"dividend_yield":1.76},{"date":"2026-04-06","close":109300,"per":20.82,"pbr":1.3,"eps":5251,"bps":84137,"roe":6.54,"debt_ratio":88.38,"market_cap":3063000000000,"dividend_yield":1.55},{"date":"2026-04-07","close":102100,"per":19.44,"pbr":1.21,"eps":5251,"bps":84137,"roe":6.54,"debt_ratio":88.38,"market_cap":2861200000000,"dividend_yield":1.66},{"date":"2026-04-08","close":103700,"per":19.75,"pbr":1.23,"eps":5251,"bps":84137,"roe":6.54,"debt_ratio":88.38,"market_cap":2906100000000,"dividend_yield":1.64},{"date":"2026-04-09","close":102800,"per":19.58,"pbr":1.22,"eps":5251,"bps":84137,"roe":6.54,"debt_ratio":88.38,"market_cap":2880800000000,"dividend_yield":1.65},{"date":"2026-04-10","close":99500,"per":18.95,"pbr":1.18,"eps":5251,"bps":84137,"roe":6.54,"debt_ratio":88.38,"market_cap":2788400000000,"dividend_yield":1.71},{"date":"2026-04-13","close":99500,"per":18.95,"pbr":1.18,"eps":5251,"bps":84137,"roe":6.54,"debt_ratio":88.38,"market_cap":2788400000000,"dividend_yield":1.71},{"date":"2026-04-14","close":100700,"per":19.18,"pbr":1.2,"eps":5251,"bps":84137,"roe":6.54,"debt_ratio":88.38,"market_cap":2822000000000,"dividend_yield":1.69},{"date":"2026-04-15","close":100600,"per":19.16,"pbr":1.2,"eps":5251,"bps":84137,"roe":6.54,"debt_ratio":88.38,"market_cap":2819200000000,"dividend_yield":1.69},{"date":"2026-04-16","close":102100,"per":19.44,"pbr":1.21,"eps":5251,"bps":84137,"roe":6.54,"debt_ratio":88.38,"market_cap":2861200000000,"dividend_yield":1.66},{"date":"2026-04-17","close":101900,"per":19.41,"pbr":1.21,"eps":5251,"bps":84137,"roe":6.54,"debt_ratio":88.38,"market_cap":2855600000000,"dividend_yield":1.67},{"date":"2026-04-20","close":100800,"per":19.2,"pbr":1.2,"eps":5251,"bps":84137,"roe":6.54,"debt_ratio":88.38,"market_cap":2824800000000,"dividend_yield":1.69},{"date":"2026-04-21","close":99900,"per":19.02,"pbr":1.19,"eps":5251,"bps":84137,"roe":6.54,"debt_ratio":88.38,"market_cap":2799600000000,"dividend_yield":1.7},{"date":"2026-04-22","close":101400,"per":19.31,"pbr":1.21,"eps":5251,"bps":84137,"roe":6.54,"debt_ratio":88.38,"market_cap":2841600000000,"dividend_yield":1.68},{"date":"2026-04-23","close":99700,"per":18.99,"pbr":1.18,"eps":5251,"bps":84137,"roe":6.54,"debt_ratio":88.38,"market_cap":2794000000000,"dividend_yield":1.71},{"date":"2026-04-24","close":100500,"per":19.14,"pbr":1.19,"eps":5251,"bps":84137,"roe":6.54,"debt_ratio":88.38,"market_cap":2816400000000,"dividend_yield":1.69},{"date":"2026-04-27","close":100600,"per":19.16,"pbr":1.2,"eps":5251,"bps":84137,"roe":6.54,"debt_ratio":88.38,"market_cap":2819200000000,"dividend_yield":1.69},{"date":"2026-04-28","close":101800,"per":19.39,"pbr":1.21,"eps":5251,"bps":84137,"roe":6.54,"debt_ratio":88.38,"market_cap":2852800000000,"dividend_yield":1.67},{"date":"2026-04-29","close":102000,"per":19.42,"pbr":1.21,"eps":5251,"bps":84137,"roe":6.54,"debt_ratio":88.38,"market_cap":2858400000000,"dividend_yield":1.67},{"date":"2026-04-30","close":99200,"per":18.89,"pbr":1.18,"eps":5251,"bps":84137,"roe":6.54,"debt_ratio":88.38,"market_cap":2780000000000,"dividend_yield":1.71},{"date":"2026-05-01","close":99200,"per":18.89,"pbr":1.18,"eps":5251,"bps":84137,"roe":6.54,"debt_ratio":88.38,"market_cap":2780000000000,"dividend_yield":1.71},{"date":"2026-05-04","close":100300,"per":19.1,"pbr":1.19,"eps":5251,"bps":84137,"roe":6.54,"debt_ratio":88.38,"market_cap":2810800000000,"dividend_yield":1.7},{"date":"2026-05-05","close":100300,"per":19.1,"pbr":1.19,"eps":5251,"bps":84137,"roe":6.54,"debt_ratio":88.38,"market_cap":2810800000000,"dividend_yield":1.7},{"date":"2026-05-06","close":99300,"per":18.91,"pbr":1.18,"eps":5251,"bps":84137,"roe":6.54,"debt_ratio":88.38,"market_cap":2782800000000,"dividend_yield":1.71},{"date":"2026-05-07","close":96500,"per":18.38,"pbr":1.15,"eps":5251,"bps":84137,"roe":6.54,"debt_ratio":88.38,"market_cap":2704300000000,"dividend_yield":1.76},{"date":"2026-05-08","close":95000,"per":18.09,"pbr":1.13,"eps":5251,"bps":84137,"roe":6.54,"debt_ratio":88.38,"market_cap":2662300000000,"dividend_yield":1.79},{"date":"2026-05-11","close":93200,"per":17.75,"pbr":1.11,"eps":5251,"bps":84137,"roe":6.54,"debt_ratio":88.38,"market_cap":2611800000000,"dividend_yield":1.82},{"date":"2026-05-12","close":92100,"per":17.54,"pbr":1.09,"eps":5251,"bps":84137,"roe":6.54,"debt_ratio":88.38,"market_cap":2581000000000,"dividend_yield":1.85},{"date":"2026-05-13","close":90800,"per":17.29,"pbr":1.08,"eps":5251,"bps":84137,"roe":6.54,"debt_ratio":88.38,"market_cap":2544600000000,"dividend_yield":1.87},{"date":"2026-05-14","close":92800,"per":17.67,"pbr":1.1,"eps":5251,"bps":84137,"roe":6.54,"debt_ratio":88.38,"market_cap":2600600000000,"dividend_yield":1.83},{"date":"2026-05-15","close":87700,"per":16.7,"pbr":1.04,"eps":5251,"bps":84137,"roe":6.54,"debt_ratio":88.38,"market_cap":2457700000000,"dividend_yield":1.94},{"date":"2026-05-18","close":86000,"per":16.38,"pbr":1.02,"eps":5251,"bps":84137,"roe":6.54,"debt_ratio":88.38,"market_cap":2410000000000,"dividend_yield":1.98},{"date":"2026-05-19","close":86700,"per":16.51,"pbr":1.03,"eps":5251,"bps":84137,"roe":6.54,"debt_ratio":88.38,"market_cap":2429700000000,"dividend_yield":1.96},{"date":"2026-05-20","close":84500,"per":16.09,"pbr":1.0,"eps":5251,"bps":84137,"roe":6.54,"debt_ratio":88.38,"market_cap":2368000000000,"dividend_yield":2.01},{"date":"2026-05-21","close":85500,"per":16.28,"pbr":1.02,"eps":5251,"bps":84137,"roe":6.54,"debt_ratio":88.38,"market_cap":2396000000000,"dividend_yield":1.99},{"date":"2026-05-22","close":88000,"per":13.43,"pbr":1.02,"eps":6552,"bps":85955,"roe":6.54,"debt_ratio":88.38,"market_cap":2466100000000,"dividend_yield":1.93},{"date":"2026-05-25","close":88000,"per":13.43,"pbr":1.02,"eps":6552,"bps":85955,"roe":6.54,"debt_ratio":88.38,"market_cap":2466100000000,"dividend_yield":1.93},{"date":"2026-05-26","close":87900,"per":13.42,"pbr":1.02,"eps":6552,"bps":85955,"roe":6.54,"debt_ratio":88.38,"market_cap":2463300000000,"dividend_yield":1.93},{"date":"2026-05-27","close":83800,"per":12.79,"pbr":0.97,"eps":6552,"bps":85955,"roe":6.54,"debt_ratio":88.38,"market_cap":2348400000000,"dividend_yield":2.03},{"date":"2026-05-28","close":82500,"per":12.59,"pbr":0.96,"eps":6552,"bps":85955,"roe":6.54,"debt_ratio":88.38,"market_cap":2312000000000,"dividend_yield":2.06},{"date":"2026-05-29","close":80200,"per":12.24,"pbr":0.93,"eps":6552,"bps":85955,"roe":6.54,"debt_ratio":88.38,"market_cap":2247500000000,"dividend_yield":2.12},{"date":"2026-06-01","close":77500,"per":11.83,"pbr":0.9,"eps":6552,"bps":85955,"roe":6.54,"debt_ratio":88.38,"market_cap":2171800000000,"dividend_yield":2.19},{"date":"2026-06-02","close":74600,"per":11.39,"pbr":0.87,"eps":6552,"bps":85955,"roe":6.54,"debt_ratio":88.38,"market_cap":2090600000000,"dividend_yield":2.28},{"date":"2026-06-03","close":74600,"per":11.39,"pbr":0.87,"eps":6552,"bps":85955,"roe":6.54,"debt_ratio":88.38,"market_cap":2090600000000,"dividend_yield":2.28},{"date":"2026-06-04","close":74000,"per":11.29,"pbr":0.86,"eps":6552,"bps":85955,"roe":6.54,"debt_ratio":88.38,"market_cap":2073700000000,"dividend_yield":2.3},{"date":"2026-06-05","close":72300,"per":11.03,"pbr":0.84,"eps":6552,"bps":85955,"roe":6.54,"debt_ratio":88.38,"market_cap":2026100000000,"dividend_yield":2.35},{"date":"2026-06-08","close":67800,"per":10.35,"pbr":0.79,"eps":6552,"bps":85955,"roe":6.54,"debt_ratio":88.38,"market_cap":1900000000000,"dividend_yield":2.51},{"date":"2026-06-09","close":69100,"per":10.55,"pbr":0.8,"eps":6552,"bps":85955,"roe":6.54,"debt_ratio":88.38,"market_cap":1936400000000,"dividend_yield":2.46},{"date":"2026-06-10","close":70100,"per":10.7,"pbr":0.82,"eps":6552,"bps":85955,"roe":6.54,"debt_ratio":88.38,"market_cap":1964500000000,"dividend_yield":2.42},{"date":"2026-06-11","close":69900,"per":10.67,"pbr":0.81,"eps":6552,"bps":85955,"roe":6.54,"debt_ratio":88.38,"market_cap":1958800000000,"dividend_yield":2.43},{"date":"2026-06-12","close":73900,"per":11.28,"pbr":0.86,"eps":6552,"bps":85955,"roe":6.54,"debt_ratio":88.38,"market_cap":2070900000000,"dividend_yield":2.3},{"date":"2026-06-15","close":75500,"per":11.52,"pbr":0.88,"eps":6552,"bps":85955,"roe":6.54,"debt_ratio":88.38,"market_cap":2115800000000,"dividend_yield":2.25},{"date":"2026-06-16","close":78100,"per":11.92,"pbr":0.91,"eps":6552,"bps":85955,"roe":6.54,"debt_ratio":88.38,"market_cap":2188600000000,"dividend_yield":2.18},{"date":"2026-06-17","close":76100,"per":11.61,"pbr":0.89,"eps":6552,"bps":85955,"roe":6.54,"debt_ratio":88.38,"market_cap":2132600000000,"dividend_yield":2.23},{"date":"2026-06-18","close":73000,"per":11.14,"pbr":0.85,"eps":6552,"bps":85955,"roe":6.54,"debt_ratio":88.38,"market_cap":2045700000000,"dividend_yield":2.33},{"date":"2026-06-19","close":71000,"per":10.84,"pbr":0.83,"eps":6552,"bps":85955,"roe":6.54,"debt_ratio":88.38,"market_cap":1989700000000,"dividend_yield":2.39},{"date":"2026-06-22","close":69000,"per":10.53,"pbr":0.8,"eps":6552,"bps":85955,"roe":6.54,"debt_ratio":88.38,"market_cap":1933600000000,"dividend_yield":2.46},{"date":"2026-06-23","close":65900,"per":10.06,"pbr":0.77,"eps":6552,"bps":85955,"roe":6.54,"debt_ratio":88.38,"market_cap":1846700000000,"dividend_yield":2.58},{"date":"2026-06-24","close":68600,"per":10.47,"pbr":0.8,"eps":6552,"bps":85955,"roe":6.54,"debt_ratio":88.38,"market_cap":1922400000000,"dividend_yield":2.48},{"date":"2026-06-25","close":66100,"per":10.09,"pbr":0.77,"eps":6552,"bps":85955,"roe":6.54,"debt_ratio":88.38,"market_cap":1852400000000,"dividend_yield":2.57},{"date":"2026-06-26","close":63200,"per":9.65,"pbr":0.74,"eps":6552,"bps":85955,"roe":6.54,"debt_ratio":88.38,"market_cap":1771100000000,"dividend_yield":2.69},{"date":"2026-06-29","close":67800,"per":10.35,"pbr":0.79,"eps":6552,"bps":85955,"roe":6.54,"debt_ratio":88.38,"market_cap":1900000000000,"dividend_yield":2.51},{"date":"2026-06-30","close":64400,"per":9.83,"pbr":0.75,"eps":6552,"bps":85955,"roe":6.54,"debt_ratio":88.38,"market_cap":1804700000000,"dividend_yield":2.64},{"date":"2026-07-01","close":66100,"per":10.09,"pbr":0.77,"eps":6552,"bps":85955,"roe":6.54,"debt_ratio":88.38,"market_cap":1852400000000,"dividend_yield":2.57},{"date":"2026-07-02","close":65600,"per":10.01,"pbr":0.76,"eps":6552,"bps":85955,"roe":6.54,"debt_ratio":88.38,"market_cap":1838300000000,"dividend_yield":2.59},{"date":"2026-07-03","close":66800,"per":10.2,"pbr":0.78,"eps":6552,"bps":85955,"roe":6.54,"debt_ratio":88.38,"market_cap":1872000000000,"dividend_yield":2.55},{"date":"2026-07-06","close":68800,"per":10.5,"pbr":0.8,"eps":6552,"bps":85955,"roe":6.54,"debt_ratio":88.38,"market_cap":1928000000000,"dividend_yield":2.47},{"date":"2026-07-07","close":65900,"per":10.06,"pbr":0.77,"eps":6552,"bps":85955,"roe":6.54,"debt_ratio":88.38,"market_cap":1846700000000,"dividend_yield":2.58},{"date":"2026-07-08","close":62500,"per":9.54,"pbr":0.73,"eps":6552,"bps":85955,"roe":6.54,"debt_ratio":88.38,"market_cap":1751500000000,"dividend_yield":2.72},{"date":"2026-07-09","close":61500,"per":9.39,"pbr":0.72,"eps":6552,"bps":85955,"roe":6.54,"debt_ratio":88.38,"market_cap":1723400000000,"dividend_yield":2.76}]}