{"ticker":"375500","history":[{"date":"2026-03-27","close":65800,"per":7.63,"pbr":0.52,"eps":8625,"bps":126050,"roe":7.34,"debt_ratio":84.38,"market_cap":2546000000000,"dividend_yield":1.35},{"date":"2026-03-30","close":69200,"per":8.02,"pbr":0.55,"eps":8625,"bps":126050,"roe":7.34,"debt_ratio":84.38,"market_cap":2677500000000,"dividend_yield":1.29},{"date":"2026-03-31","close":66800,"per":7.74,"pbr":0.53,"eps":8625,"bps":126050,"roe":7.34,"debt_ratio":84.38,"market_cap":2584700000000,"dividend_yield":1.33},{"date":"2026-04-01","close":72500,"per":8.41,"pbr":0.58,"eps":8625,"bps":126050,"roe":7.34,"debt_ratio":84.38,"market_cap":2805200000000,"dividend_yield":1.23},{"date":"2026-04-02","close":68100,"per":7.9,"pbr":0.54,"eps":8625,"bps":126050,"roe":7.34,"debt_ratio":84.38,"market_cap":2635000000000,"dividend_yield":1.31},{"date":"2026-04-03","close":75000,"per":8.7,"pbr":0.6,"eps":8625,"bps":126050,"roe":7.34,"debt_ratio":84.38,"market_cap":2902000000000,"dividend_yield":1.19},{"date":"2026-04-06","close":77200,"per":8.95,"pbr":0.61,"eps":8625,"bps":126050,"roe":7.34,"debt_ratio":84.38,"market_cap":2987100000000,"dividend_yield":1.15},{"date":"2026-04-07","close":75600,"per":8.77,"pbr":0.6,"eps":8625,"bps":126050,"roe":7.34,"debt_ratio":84.38,"market_cap":2925200000000,"dividend_yield":1.18},{"date":"2026-04-08","close":95200,"per":11.04,"pbr":0.76,"eps":8625,"bps":126050,"roe":7.34,"debt_ratio":84.38,"market_cap":3683600000000,"dividend_yield":0.94},{"date":"2026-04-09","close":94300,"per":10.93,"pbr":0.75,"eps":8625,"bps":126050,"roe":7.34,"debt_ratio":84.38,"market_cap":3648800000000,"dividend_yield":0.94},{"date":"2026-04-10","close":94500,"per":10.96,"pbr":0.75,"eps":8625,"bps":126050,"roe":7.34,"debt_ratio":84.38,"market_cap":3656500000000,"dividend_yield":0.94},{"date":"2026-04-13","close":94500,"per":10.96,"pbr":0.75,"eps":8625,"bps":126050,"roe":7.34,"debt_ratio":84.38,"market_cap":3656500000000,"dividend_yield":0.94},{"date":"2026-04-14","close":99000,"per":11.48,"pbr":0.79,"eps":8625,"bps":126050,"roe":7.34,"debt_ratio":84.38,"market_cap":3830600000000,"dividend_yield":0.9},{"date":"2026-04-15","close":102500,"per":11.88,"pbr":0.81,"eps":8625,"bps":126050,"roe":7.34,"debt_ratio":84.38,"market_cap":3966000000000,"dividend_yield":0.87},{"date":"2026-04-16","close":99000,"per":11.48,"pbr":0.79,"eps":8625,"bps":126050,"roe":7.34,"debt_ratio":84.38,"market_cap":3830600000000,"dividend_yield":0.9},{"date":"2026-04-17","close":97700,"per":11.33,"pbr":0.78,"eps":8625,"bps":126050,"roe":7.34,"debt_ratio":84.38,"market_cap":3780300000000,"dividend_yield":0.91},{"date":"2026-04-20","close":95500,"per":11.07,"pbr":0.76,"eps":8625,"bps":126050,"roe":7.34,"debt_ratio":84.38,"market_cap":3695200000000,"dividend_yield":0.93},{"date":"2026-04-21","close":100600,"per":11.66,"pbr":0.8,"eps":8625,"bps":126050,"roe":7.34,"debt_ratio":84.38,"market_cap":3892500000000,"dividend_yield":0.88},{"date":"2026-04-22","close":98000,"per":11.36,"pbr":0.78,"eps":8625,"bps":126050,"roe":7.34,"debt_ratio":84.38,"market_cap":3791900000000,"dividend_yield":0.91},{"date":"2026-04-23","close":97600,"per":11.32,"pbr":0.77,"eps":8625,"bps":126050,"roe":7.34,"debt_ratio":84.38,"market_cap":3776400000000,"dividend_yield":0.91},{"date":"2026-04-24","close":99000,"per":11.48,"pbr":0.79,"eps":8625,"bps":126050,"roe":7.34,"debt_ratio":84.38,"market_cap":3830600000000,"dividend_yield":0.9},{"date":"2026-04-27","close":98300,"per":11.4,"pbr":0.78,"eps":8625,"bps":126050,"roe":7.34,"debt_ratio":84.38,"market_cap":3803500000000,"dividend_yield":0.9},{"date":"2026-04-28","close":99900,"per":11.58,"pbr":0.79,"eps":8625,"bps":126050,"roe":7.34,"debt_ratio":84.38,"market_cap":3865400000000,"dividend_yield":0.89},{"date":"2026-04-29","close":101100,"per":11.72,"pbr":0.8,"eps":8625,"bps":126050,"roe":7.34,"debt_ratio":84.38,"market_cap":3911900000000,"dividend_yield":0.88},{"date":"2026-04-30","close":99000,"per":11.48,"pbr":0.79,"eps":8625,"bps":126050,"roe":7.34,"debt_ratio":84.38,"market_cap":3830600000000,"dividend_yield":0.9},{"date":"2026-05-01","close":99000,"per":11.48,"pbr":0.79,"eps":8625,"bps":126050,"roe":7.34,"debt_ratio":84.38,"market_cap":3830600000000,"dividend_yield":0.9},{"date":"2026-05-04","close":91300,"per":10.59,"pbr":0.72,"eps":8625,"bps":126050,"roe":7.34,"debt_ratio":84.38,"market_cap":3532700000000,"dividend_yield":0.98},{"date":"2026-05-05","close":91300,"per":10.59,"pbr":0.72,"eps":8625,"bps":126050,"roe":7.34,"debt_ratio":84.38,"market_cap":3532700000000,"dividend_yield":0.98},{"date":"2026-05-06","close":93100,"per":10.79,"pbr":0.74,"eps":8625,"bps":126050,"roe":7.34,"debt_ratio":84.38,"market_cap":3602300000000,"dividend_yield":0.96},{"date":"2026-05-07","close":100300,"per":11.63,"pbr":0.8,"eps":8625,"bps":126050,"roe":7.34,"debt_ratio":84.38,"market_cap":3880900000000,"dividend_yield":0.89},{"date":"2026-05-08","close":95400,"per":11.06,"pbr":0.76,"eps":8625,"bps":126050,"roe":7.34,"debt_ratio":84.38,"market_cap":3691300000000,"dividend_yield":0.93}]}